CHANGELOG.rst
openldap_acl_test/__init__.py
openldap_acl_test/cli.py
openldap_acl_test/conf.py
openldap_acl_test/exceptions.py
openldap_acl_test/log.py
openldap_acl_test/py.typed
openldap_acl_test/testcase.py
openldap_acl_test-1.0.1.dist-info/entry_points.txt
openldap_acl_test-1.0.1.dist-info/LICENSE
openldap_acl_test-1.0.1.dist-info/WHEEL
openldap_acl_test-1.0.1.dist-info/METADATA
openldap_acl_test-1.0.1.dist-info/RECORD
