Metadata-Version: 2.1
Name: openldap-acl-test
Version: 1.0.1
Summary: OpenLDAP ACL check tool
Home-page: https://github.com/mypaceshun/openldap-acl-test
License: MIT
Author: KAWAI Shun
Author-email: mypaceshun@gmail.com
Requires-Python: >=3.9,<4.0
Classifier: License :: OSI Approved :: MIT License
Classifier: Programming Language :: Python :: 3
Classifier: Programming Language :: Python :: 3.10
Classifier: Programming Language :: Python :: 3.9
Requires-Dist: PyYAML (>=6.0,<7.0)
Requires-Dist: click (>=8.1.3,<9.0.0)
Project-URL: Repository, https://github.com/mypaceshun/openldap-acl-test
